{
  "id": "W23-G23",
  "platform": "pinterest",
  "type": "pin",
  "image": "2026-05-28-eu-blind-spot-pinterest.png",
  "title": "EU buyers can't buy your prints. Here's why.",
  "description": "Most US Etsy sellers list only inch-based sizes — 4×6, 8×10, 8×12. EU, UK, and Australian buyers need A4, A3, and A5. Without ISO files your listing is invisible to 40%+ of the market. SnapToSize generates the full ISO pack (A5, A4, A3, A2, A1) at 300 DPI in one upload. snaptosize.com",
  "board": "digital-prints",
  "board_id": "1056882982543897931",
  "link": "https://snaptosize.com",
  "created": "2026-05-28",
  "scheduled_for": "2026-05-29T13:00:00Z",
  "r2_url": "https://social.snaptosize.com/content/pinterest/2026-05-28-eu-blind-spot-pinterest/2026-05-28-eu-blind-spot-pinterest.jpg",
  "buffer_post_id": "6a17fa4c84011986fb3cfafc"
}